nsj_flask_utils/__init__.py
nsj_flask_utils/daos/__init__.py
nsj_flask_utils/daos/base_dao.py
nsj_flask_utils/dtos/__init__.py
nsj_flask_utils/dtos/base_dto.py
nsj_flask_utils/exceptions/__init__.py
nsj_flask_utils/py.typed
nsj_flask_utils/service/__init__.py
nsj_flask_utils/service/base_service.py
nsj_flask_utils/utils/__init__.py
nsj_flask_utils/utils/error_handlers.py
nsj_flask_utils/utils/filter_params.py
nsj_flask_utils/utils/injector_factory.py
nsj_flask_utils/utils/json.py
nsj_flask_utils/utils/pagination_params.py
nsj_flask_utils/utils/request_args.py
nsj_flask_utils-0.2.0.dist-info/METADATA
nsj_flask_utils-0.2.0.dist-info/WHEEL
nsj_flask_utils-0.2.0.dist-info/RECORD
