Metadata-Version: 2.1
Name: nsj-flask-utils
Version: 0.2.0
Summary: Utils for Flask
License: MIT
Author: Vinicius Teshima
Author-email: viniciusteshima@nasajon.com.br
Requires-Python: ==3.11.4
Classifier: License :: OSI Approved :: MIT License
Classifier: Programming Language :: Python :: 3
Requires-Dist: Flask (>=2.3.2,<3.0.0)
Requires-Dist: SQLAlchemy (>=2.0.19,<3.0.0)
Requires-Dist: flask-sqlalchemy (>=3.0.5,<4.0.0)
Requires-Dist: pydantic (>=2.1.1,<3.0.0)
